flask_file_routes/__init__.py
flask_file_routes/ctx.py
flask_file_routes/view.py
flask_file_routes-0.3.2.dist-info/WHEEL
flask_file_routes-0.3.2.dist-info/METADATA
flask_file_routes-0.3.2.dist-info/RECORD
