Metadata-Version: 2.4
Name: flask-file-routes
Version: 0.3.2
Summary: File-based routing with a new mix-code file format that combines python code and a jinja template
Author: Maxime Bouroumeau-Fuseau
Author-email: Maxime Bouroumeau-Fuseau <maxime.bouroumeau@gmail.com>
License-Expression: MIT
Requires-Dist: flask~=3.0
Requires-Dist: jinjapy~=0.1
Requires-Dist: markdown~=3.8
Requires-Dist: pyyaml~=6.0
Requires-Python: >=3.10
Project-URL: Repository, https://github.com/hyperflask/flask-file-routes
